setup.py
petname/__init__.py
petname/__main__.py
petname/english.py
petname.egg-info/PKG-INFO
petname.egg-info/SOURCES.txt
petname.egg-info/dependency_links.txt
petname.egg-info/entry_points.txt
petname.egg-info/top_level.txt