Metadata-Version: 1.0
Name: petname
Version: 1.8
Summary: Generate human-readable, random object names
Home-page: https://launchpad.net/petname
Author: Dustin Kirkland
Author-email: dustin.kirkland@gmail.com
License: Apache2
Keywords: random name uuid
Platform: any
